miu_studio/__init__.py
miu_studio/__main__.py
miu_studio/main.py
miu_studio/api/__init__.py
miu_studio/api/routes/__init__.py
miu_studio/api/routes/chat.py
miu_studio/api/routes/health.py
miu_studio/api/routes/sessions.py
miu_studio/core/__init__.py
miu_studio/core/config.py
miu_studio/models/__init__.py
miu_studio/models/api.py
miu_studio/services/__init__.py
miu_studio/services/chat_service.py
miu_studio/services/session_manager.py
miu_studio/static/app.js
miu_studio/static/index.html
miu_studio-1.0.0.dist-info/METADATA
miu_studio-1.0.0.dist-info/WHEEL
miu_studio-1.0.0.dist-info/entry_points.txt
miu_studio-1.0.0.dist-info/RECORD
