Metadata-Version: 2.4
Name: miu-studio
Version: 1.0.0
Summary: Web server for miu AI agent
Project-URL: Homepage, https://github.com/vanducng/miumono
Project-URL: Repository, https://github.com/vanducng/miumono
License: MIT
Classifier: Development Status :: 3 - Alpha
Classifier: Environment :: Web Environment
Classifier: Framework :: FastAPI
Classifier: Intended Audience :: Developers
Classifier: License :: OSI Approved :: MIT License
Classifier: Programming Language :: Python :: 3.11
Classifier: Programming Language :: Python :: 3.12
Classifier: Programming Language :: Python :: 3.13
Requires-Python: >=3.11
Requires-Dist: aiofiles>=23.0
Requires-Dist: fastapi>=0.115
Requires-Dist: miu-core[anthropic]
Requires-Dist: pydantic-settings>=2.6
Requires-Dist: uvicorn[standard]>=0.32
Requires-Dist: websockets>=13.0
